{
  "image_filename": "000014417332878671",
  "objects": [
    {
      "shape": "Icosahedron",
      "size": 1.5,
      "material": "data/materials/PoliigonBricksPaintedWhite001.blend",
      "3d_coords": [
        1.8868227005004883,
        -2.4972338676452637,
        1.5
      ],
      "rotation": 0.0,
      "pixel_coords": [
        51,
        65,
        7.801423072814941
      ]
    },
    {
      "shape": "Cube",
      "size": 1.5,
      "material": "data/materials/PoliigonFabricFleece001.blend",
      "3d_coords": [
        1.7177820205688477,
        2.6186182498931885,
        1.5
      ],
      "rotation": 0.0,
      "pixel_coords": [
        104,
        45,
        10.82530689239502
      ]
    }
  ],
  "ground_material": "data/materials/PoliigonBricksFlemishRed001.blend",
  "Lamp_Key": [
    7.0928192138671875,
    -3.666670560836792,
    3.742547035217285
  ],
  "Lamp_Back": [
    -1.571437954902649,
    1.9231065511703491,
    6.313754558563232
  ],
  "Lamp_Fill": [
    -3.9568889141082764,
    -3.7317955493927,
    3.612853527069092
  ],
  "Camera": [
    7.716257572174072,
    -6.36231803894043,
    5.031217575073242
  ]
}