{
  "Camera": [
    7.596061706542969,
    -6.971302509307861,
    5.716409206390381
  ],
  "image_filename": "000009667378725117",
  "objects": [
    {
      "rotation": 0.0,
      "color": [
        1.0,
        0.0,
        1.0,
        1.0
      ],
      "pixel_coords": [
        96,
        59,
        9.275677680969238
      ],
      "shape": "SmoothCube_v2",
      "3d_coords": [
        2.9459214210510254,
        0.19004622101783752,
        1.5
      ],
      "size": 1.5,
      "material": "Rubber"
    },
    {
      "rotation": 0.0,
      "color": [
        0.0,
        1.0,
        0.0,
        1.0
      ],
      "pixel_coords": [
        84,
        43,
        11.899664878845215
      ],
      "shape": "Sphere",
      "3d_coords": [
        0.42282241582870483,
        1.8781275749206543,
        1.5
      ],
      "size": 1.5,
      "material": "MyMetal"
    }
  ],
  "Lamp_Key": [
    6.633666038513184,
    -2.1295433044433594,
    4.859251022338867
  ],
  "Lamp_Back": [
    -0.8659613728523254,
    3.338519811630249,
    5.6192097663879395
  ],
  "Lamp_Fill": [
    -3.6738851070404053,
    -3.2609596252441406,
    2.1012134552001953
  ]
}