{
  "image_filename": "00000038",
  "objects": [
    {
      "shape": "square",
      "size": 0.225,
      "rotation": 0.0,
      "2d_coords": [
        0.5727664801756363,
        0.8794716622689988
      ],
      "color": [
        0,
        127,
        255
      ]
    },
    {
      "shape": "star_4",
      "size": 0.125,
      "rotation": 0.0,
      "2d_coords": [
        0.06518450603303573,
        0.6768341876313052
      ],
      "color": [
        0,
        255,
        0
      ]
    }
  ]
}