{
  "objects": [
    {
      "shape": "Suzanne",
      "color": [
        0.0,
        0.0,
        1.0,
        1.0
      ],
      "pixel_coords": [
        19,
        52,
        11.210164070129395
      ],
      "3d_coords": [
        -2.3290953636169434,
        -2.728503942489624,
        1.0
      ],
      "size": 1.0,
      "rotation": 0.0,
      "material": "Rubber"
    },
    {
      "shape": "Suzanne",
      "color": [
        1.0,
        0.0,
        0.0,
        1.0
      ],
      "pixel_coords": [
        78,
        43,
        13.092752456665039
      ],
      "3d_coords": [
        -0.999194324016571,
        2.464679002761841,
        1.0
      ],
      "size": 1.0,
      "rotation": 0.0,
      "material": "Rubber"
    }
  ],
  "Camera": [
    7.938451290130615,
    -6.227224349975586,
    5.663054466247559
  ],
  "Lamp_Key": [
    5.824968338012695,
    -2.6780436038970947,
    4.220920562744141
  ],
  "Lamp_Fill": [
    -4.2722015380859375,
    -4.7244086265563965,
    2.148340940475464
  ],
  "image_filename": "000009070050929059",
  "Lamp_Back": [
    -0.5640255808830261,
    2.5411484241485596,
    6.487318515777588
  ]
}