{
  "Lamp_Fill": [
    -4.215282917022705,
    -3.2864890098571777,
    3.1987602710723877
  ],
  "Lamp_Key": [
    6.269225597381592,
    -2.320110321044922,
    4.074819087982178
  ],
  "Lamp_Back": [
    -1.8946659564971924,
    2.546623468399048,
    5.215470790863037
  ],
  "Camera": [
    7.89723014831543,
    -6.2646589279174805,
    5.709374904632568
  ],
  "image_filename": "000000980150099357",
  "objects": [
    {
      "pixel_coords": [
        46,
        66,
        9.321160316467285
      ],
      "size": 1.0,
      "rotation": 0.0,
      "shape": "Sphere",
      "material": "Rubber",
      "3d_coords": [
        0.8623928427696228,
        -2.187645673751831,
        1.0
      ],
      "color": [
        0.0,
        1.0,
        1.0,
        1.0
      ]
    },
    {
      "pixel_coords": [
        88,
        49,
        10.454536437988281
      ],
      "size": 1.5,
      "rotation": 0.0,
      "shape": "SmoothCylinder",
      "material": "MyMetal",
      "3d_coords": [
        1.4451433420181274,
        1.0985357761383057,
        1.5
      ],
      "color": [
        1.0,
        0.0,
        1.0,
        1.0
      ]
    }
  ]
}