{
  "image_filename": "000012326230160406",
  "objects": [
    {
      "shape": "Cone",
      "size": 1.5,
      "material": "data/materials/PoliigonBricksPaintedWhite001.blend",
      "3d_coords": [
        -2.9631850719451904,
        -0.17719876766204834,
        1.5
      ],
      "rotation": 0.0,
      "pixel_coords": [
        40,
        38,
        12.404247283935547
      ]
    },
    {
      "shape": "Cube",
      "size": 2.0,
      "material": "data/materials/PoliigonFabricDenim003.blend",
      "3d_coords": [
        1.831485390663147,
        -0.1817043274641037,
        2.0
      ],
      "rotation": 0.0,
      "pixel_coords": [
        81,
        46,
        8.974272727966309
      ]
    }
  ],
  "ground_material": "data/materials/PoliigonBricksFlemishRed001.blend",
  "Lamp_Key": [
    7.321080684661865,
    -3.6634888648986816,
    3.4468178749084473
  ],
  "Lamp_Back": [
    -0.9131940007209778,
    3.512399196624756,
    6.374691009521484
  ],
  "Lamp_Fill": [
    -4.4795732498168945,
    -3.3410658836364746,
    3.6760740280151367
  ],
  "Camera": [
    7.484020709991455,
    -6.682165145874023,
    4.964731693267822
  ]
}