{
  "image_filename": "000013565724098695",
  "objects": [
    {
      "rotation": 0.0,
      "color": [
        0.0,
        1.0,
        1.0,
        1.0
      ],
      "pixel_coords": [
        82,
        55,
        10.874419212341309
      ],
      "shape": "SmoothCylinder",
      "material": "Rubber",
      "3d_coords": [
        1.2301065921783447,
        0.7424597144126892,
        1.0
      ],
      "size": 1.0
    },
    {
      "rotation": 0.0,
      "color": [
        1.0,
        0.0,
        1.0,
        1.0
      ],
      "pixel_coords": [
        46,
        50,
        9.135531425476074
      ],
      "shape": "SmoothCube_v2",
      "material": "Rubber",
      "3d_coords": [
        0.662803590297699,
        -2.1240105628967285,
        2.0
      ],
      "size": 2.0
    }
  ],
  "Lamp_Key": [
    6.598357200622559,
    -3.2029953002929688,
    4.716738224029541
  ],
  "Camera": [
    7.864895343780518,
    -6.758087158203125,
    5.504398345947266
  ],
  "Lamp_Back": [
    -0.5139324069023132,
    3.310000419616699,
    5.147994041442871
  ],
  "Lamp_Fill": [
    -4.141957759857178,
    -3.853287935256958,
    3.8945868015289307
  ]
}