{
  "Lamp_Key": [
    6.566603660583496,
    -3.61360764503479,
    5.012104034423828
  ],
  "image_filename": "000013482486577223",
  "Lamp_Back": [
    -1.0881688594818115,
    3.576143741607666,
    6.483828544616699
  ],
  "Lamp_Fill": [
    -4.319127559661865,
    -3.658970355987549,
    2.7604429721832275
  ],
  "Camera": [
    7.1699347496032715,
    -6.09891414642334,
    5.259047985076904
  ],
  "objects": [
    {
      "rotation": 0.0,
      "shape": "SmoothCylinder",
      "color": [
        0.0,
        1.0,
        0.0,
        1.0
      ],
      "pixel_coords": [
        84,
        45,
        10.265371322631836
      ],
      "size": 1.5,
      "material": "MyMetal",
      "3d_coords": [
        0.7423499822616577,
        1.2519023418426514,
        1.5
      ]
    },
    {
      "rotation": 0.0,
      "shape": "Suzanne",
      "color": [
        1.0,
        0.0,
        0.0,
        1.0
      ],
      "pixel_coords": [
        41,
        51,
        9.273929595947266
      ],
      "size": 1.5,
      "material": "MyMetal",
      "3d_coords": [
        -0.29867666959762573,
        -1.7247437238693237,
        1.5
      ]
    }
  ]
}