{
  "image_filename": "000010061233266896",
  "objects": [
    {
      "shape": "Cylinder",
      "size": 2.0,
      "material": "data/materials/PoliigonFabricDenim003.blend",
      "3d_coords": [
        -1.9625701904296875,
        -2.3007519245147705,
        2.0
      ],
      "rotation": 0.0,
      "pixel_coords": [
        21,
        40,
        9.932851791381836
      ]
    },
    {
      "shape": "Cone",
      "size": 2.0,
      "material": "data/materials/PoliigonFabricDenim003.blend",
      "3d_coords": [
        1.750101089477539,
        1.844568133354187,
        2.0
      ],
      "rotation": 0.0,
      "pixel_coords": [
        99,
        40,
        10.057356834411621
      ]
    }
  ],
  "ground_material": "data/materials/PoliigonMetalSpottyDiscoloration001.blend",
  "Lamp_Key": [
    7.019012928009033,
    -1.9861259460449219,
    3.30800724029541
  ],
  "Lamp_Back": [
    -0.8041335344314575,
    2.377951145172119,
    4.904530048370361
  ],
  "Lamp_Fill": [
    -4.229361534118652,
    -3.1510555744171143,
    3.5235073566436768
  ],
  "Camera": [
    7.059686183929443,
    -6.6535773277282715,
    5.208776473999023
  ]
}