{
  "Lamp_Fill": [
    -4.0657806396484375,
    -4.704313278198242,
    2.427635908126831
  ],
  "Camera": [
    7.063526153564453,
    -6.192856788635254,
    5.002689361572266
  ],
  "Lamp_Back": [
    -1.8324267864227295,
    3.452166795730591,
    5.8996429443359375
  ],
  "Lamp_Key": [
    5.915106773376465,
    -2.939765214920044,
    3.595489978790283
  ],
  "image_filename": "000016223603738012",
  "objects": [
    {
      "3d_coords": [
        2.8675038814544678,
        -0.12736870348453522,
        1.0
      ],
      "shape": "Sphere",
      "rotation": 0.0,
      "pixel_coords": [
        95,
        67,
        8.195645332336426
      ],
      "material": "MyMetal",
      "color": [
        0.0,
        1.0,
        0.0,
        1.0
      ],
      "size": 1.0
    },
    {
      "3d_coords": [
        -2.6357181072235107,
        2.588334798812866,
        1.5
      ],
      "shape": "SmoothCube_v2",
      "rotation": 0.0,
      "pixel_coords": [
        66,
        32,
        13.193216323852539
      ],
      "material": "MyMetal",
      "color": [
        1.0,
        0.0,
        0.0,
        1.0
      ],
      "size": 1.5
    }
  ]
}