{
  "image_filename": "000000986891814366",
  "objects": [
    {
      "shape": "Cylinder",
      "size": 1.5,
      "material": "data/materials/PoliigonChainmailCopperRoundedThin001.blend",
      "3d_coords": [
        1.8133560419082642,
        -2.132002830505371,
        1.5
      ],
      "rotation": 0.0,
      "pixel_coords": [
        55,
        63,
        7.796645164489746
      ]
    },
    {
      "shape": "Cylinder",
      "size": 2.0,
      "material": "data/materials/PoliigonWoodFlooring061.blend",
      "3d_coords": [
        -2.3171846866607666,
        -1.6232746839523315,
        2.0
      ],
      "rotation": 0.0,
      "pixel_coords": [
        28,
        36,
        10.678909301757812
      ]
    }
  ],
  "ground_material": "data/materials/PoliigonMetalSpottyDiscoloration001.blend",
  "Lamp_Key": [
    7.141852378845215,
    -3.0213634967803955,
    4.081458568572998
  ],
  "Lamp_Back": [
    -1.1575087308883667,
    3.3270909786224365,
    5.744875907897949
  ],
  "Lamp_Fill": [
    -4.403792381286621,
    -4.313487529754639,
    3.943812847137451
  ],
  "Camera": [
    7.500336647033691,
    -6.070817470550537,
    5.13308572769165
  ]
}