{
  "Camera": [
    7.58205509185791,
    -6.04373836517334,
    5.313083171844482
  ],
  "Lamp_Key": [
    5.97114372253418,
    -3.124767303466797,
    4.535002708435059
  ],
  "Lamp_Back": [
    -0.2769644558429718,
    1.746599555015564,
    6.1667962074279785
  ],
  "image_filename": "000006429140462228",
  "Lamp_Fill": [
    -4.842962265014648,
    -4.446535587310791,
    2.0464282035827637
  ],
  "objects": [
    {
      "shape": "SmoothCube_v2",
      "size": 1.5,
      "material": "Rubber",
      "3d_coords": [
        1.976314663887024,
        1.4419091939926147,
        1.5
      ],
      "rotation": 0.0,
      "pixel_coords": [
        98,
        50,
        9.768450736999512
      ],
      "color": [
        1.0,
        0.0,
        1.0,
        1.0
      ]
    },
    {
      "shape": "SmoothCylinder",
      "size": 2.0,
      "material": "Rubber",
      "3d_coords": [
        0.7925035357475281,
        -2.728487968444824,
        2.0
      ],
      "rotation": 0.0,
      "pixel_coords": [
        36,
        53,
        8.06032943725586
      ],
      "color": [
        0.0,
        0.0,
        1.0,
        1.0
      ]
    }
  ]
}