{
  "Lamp_Key": [
    6.062099456787109,
    -2.294193744659424,
    4.723644733428955
  ],
  "objects": [
    {
      "pixel_coords": [
        48,
        59,
        7.188377380371094
      ],
      "size": 2.0,
      "3d_coords": [
        1.8202500343322754,
        -2.7626559734344482,
        2.0
      ],
      "color": [
        1.0,
        1.0,
        0.0,
        1.0
      ],
      "shape": "Sphere",
      "rotation": 0.0,
      "material": "MyMetal"
    },
    {
      "pixel_coords": [
        65,
        28,
        12.891274452209473
      ],
      "size": 2.0,
      "3d_coords": [
        -2.350529909133911,
        2.2562992572784424,
        2.0
      ],
      "color": [
        0.0,
        0.0,
        1.0,
        1.0
      ],
      "shape": "SmoothCube_v2",
      "rotation": 0.0,
      "material": "Rubber"
    }
  ],
  "Lamp_Fill": [
    -4.339017868041992,
    -3.6442956924438477,
    2.6393821239471436
  ],
  "image_filename": "000010732365921316",
  "Camera": [
    7.175708293914795,
    -6.485140800476074,
    5.144969940185547
  ],
  "Lamp_Back": [
    -0.47800305485725403,
    1.6906609535217285,
    5.509871482849121
  ]
}