{
  "Camera": [
    7.954990386962891,
    -6.105777263641357,
    5.555838108062744
  ],
  "Lamp_Fill": [
    -5.272430896759033,
    -3.3425650596618652,
    2.4202160835266113
  ],
  "Lamp_Back": [
    -1.7582541704177856,
    2.365927219390869,
    5.170130252838135
  ],
  "image_filename": "000008575116011164",
  "objects": [
    {
      "color": [
        1.0,
        0.0,
        1.0,
        1.0
      ],
      "pixel_coords": [
        58,
        50,
        10.18477725982666
      ],
      "rotation": 0.0,
      "material": "Rubber",
      "3d_coords": [
        0.2526474595069885,
        -0.7083497643470764,
        1.5
      ],
      "shape": "SmoothCube_v2",
      "size": 1.5
    },
    {
      "color": [
        0.0,
        1.0,
        1.0,
        1.0
      ],
      "pixel_coords": [
        23,
        56,
        10.436094284057617
      ],
      "rotation": 0.0,
      "material": "MyMetal",
      "3d_coords": [
        -1.3805148601531982,
        -2.819225549697876,
        1.0
      ],
      "shape": "Suzanne",
      "size": 1.0
    }
  ],
  "Lamp_Key": [
    7.35028076171875,
    -2.5117855072021484,
    4.689010143280029
  ]
}