{
  "Lamp_Key": [
    5.943249702453613,
    -3.8525004386901855,
    5.112196445465088
  ],
  "Lamp_Back": [
    -1.5756807327270508,
    3.16365385055542,
    4.899926662445068
  ],
  "objects": [
    {
      "size": 2.0,
      "material": "MyMetal",
      "rotation": 0.0,
      "shape": "Sphere",
      "3d_coords": [
        1.524631381034851,
        -2.8625314235687256,
        2.0
      ],
      "pixel_coords": [
        40,
        56,
        7.2076497077941895
      ],
      "color": [
        0.0,
        1.0,
        1.0,
        1.0
      ]
    },
    {
      "size": 1.0,
      "material": "Rubber",
      "rotation": 0.0,
      "shape": "Suzanne",
      "3d_coords": [
        2.859998941421509,
        2.5725643634796143,
        1.0
      ],
      "pixel_coords": [
        118,
        55,
        9.821557998657227
      ],
      "color": [
        0.0,
        1.0,
        0.0,
        1.0
      ]
    }
  ],
  "Camera": [
    7.414386749267578,
    -6.106149196624756,
    4.9073967933654785
  ],
  "Lamp_Fill": [
    -5.470248699188232,
    -3.017789840698242,
    3.319988965988159
  ],
  "image_filename": "000000570630974797"
}