{
  "image_filename": "000003694949742825",
  "objects": [
    {
      "shape": "Torus",
      "size": 1.5,
      "material": "data/materials/PoliigonBricksFlemishRed001.blend",
      "3d_coords": [
        -2.4261093139648438,
        -2.6484017372131348,
        1.5
      ],
      "rotation": 0.0,
      "pixel_coords": [
        16,
        46,
        10.411444664001465
      ]
    },
    {
      "shape": "Torus",
      "size": 1.0,
      "material": "data/materials/PoliigonBricksFlemishRed001.blend",
      "3d_coords": [
        1.022706389427185,
        0.12422975152730942,
        1.0
      ],
      "rotation": 0.0,
      "pixel_coords": [
        75,
        56,
        10.070259094238281
      ]
    }
  ],
  "ground_material": "data/materials/PoliigonChainmailCopperRoundedThin001.blend",
  "Lamp_Key": [
    6.521288871765137,
    -2.837583541870117,
    3.9354140758514404
  ],
  "Lamp_Back": [
    -1.8578661680221558,
    2.801037549972534,
    5.79293966293335
  ],
  "Lamp_Fill": [
    -4.75004768371582,
    -3.795711040496826,
    3.6276633739471436
  ],
  "Camera": [
    7.206480979919434,
    -6.641759872436523,
    5.280815124511719
  ]
}