{
  "objects": [
    {
      "material": "MyMetal",
      "3d_coords": [
        1.108161211013794,
        -0.3695541024208069,
        1.5
      ],
      "shape": "SmoothCube_v2",
      "pixel_coords": [
        70,
        53,
        9.37921142578125
      ],
      "size": 1.5,
      "color": [
        1.0,
        0.0,
        1.0,
        1.0
      ],
      "rotation": 0.0
    },
    {
      "material": "Rubber",
      "3d_coords": [
        -2.4671530723571777,
        -0.8589267134666443,
        1.0
      ],
      "shape": "SmoothCube_v2",
      "pixel_coords": [
        37,
        46,
        11.746906280517578
      ],
      "size": 1.0,
      "color": [
        0.0,
        1.0,
        1.0,
        1.0
      ],
      "rotation": 0.0
    }
  ],
  "Camera": [
    7.390972137451172,
    -6.093791961669922,
    5.558108329772949
  ],
  "Lamp_Fill": [
    -4.961437225341797,
    -3.578169345855713,
    2.1344990730285645
  ],
  "Lamp_Key": [
    5.728832721710205,
    -2.064333438873291,
    4.298142433166504
  ],
  "image_filename": "000010270457125534",
  "Lamp_Back": [
    -1.4944566488265991,
    1.6708892583847046,
    5.056579113006592
  ]
}