{
  "Lamp_Back": [
    -1.1420789957046509,
    2.0266146659851074,
    6.280961513519287
  ],
  "image_filename": "000011177626465584",
  "Camera": [
    7.9429545402526855,
    -6.291360378265381,
    5.066405773162842
  ],
  "objects": [
    {
      "rotation": 0.0,
      "shape": "SmoothCylinder",
      "material": "Rubber",
      "color": [
        0.0,
        0.0,
        1.0,
        1.0
      ],
      "size": 2.0,
      "3d_coords": [
        -1.6520484685897827,
        -1.1809064149856567,
        2.0
      ],
      "pixel_coords": [
        39,
        38,
        10.936795234680176
      ]
    },
    {
      "rotation": 0.0,
      "shape": "Suzanne",
      "material": "MyMetal",
      "color": [
        0.0,
        1.0,
        1.0,
        1.0
      ],
      "size": 1.0,
      "3d_coords": [
        2.9013583660125732,
        -2.2468297481536865,
        1.0
      ],
      "pixel_coords": [
        65,
        78,
        7.599510669708252
      ]
    }
  ],
  "Lamp_Fill": [
    -4.451930046081543,
    -4.688051700592041,
    2.3680970668792725
  ],
  "Lamp_Key": [
    6.662326812744141,
    -3.514739990234375,
    3.7766103744506836
  ]
}