{
  "image_filename": "000010451559691277",
  "objects": [
    {
      "shape": "Suzanne",
      "size": 2.0,
      "material": "data/materials/PoliigonMetalSpottyDiscoloration001.blend",
      "3d_coords": [
        -2.0355441570281982,
        2.0018928050994873,
        2.0
      ],
      "rotation": 0.0,
      "pixel_coords": [
        66,
        29,
        12.579499244689941
      ]
    },
    {
      "shape": "Suzanne",
      "size": 1.0,
      "material": "data/materials/PoliigonRoofTilesTerracotta004.blend",
      "3d_coords": [
        -1.1367448568344116,
        -1.2628798484802246,
        1.0
      ],
      "rotation": 0.0,
      "pixel_coords": [
        42,
        53,
        10.666387557983398
      ]
    }
  ],
  "ground_material": "data/materials/PoliigonBricksFlemishRed001.blend",
  "Lamp_Key": [
    6.821422576904297,
    -2.6655235290527344,
    5.129150390625
  ],
  "Lamp_Back": [
    -0.6741154193878174,
    2.5096771717071533,
    5.925300598144531
  ],
  "Lamp_Fill": [
    -4.853282928466797,
    -4.723796367645264,
    2.3940136432647705
  ],
  "Camera": [
    7.140471458435059,
    -6.356753826141357,
    5.789459705352783
  ]
}